athena_pkg/AthenaQueryEngine.py
athena_pkg/QueryEngine.py
athena_pkg/__init__.py
athena_pkg/data.py
athena_pkg/statistics.py
lv_athena_pkg-0.0.3.dist-info/LICENSE
lv_athena_pkg-0.0.3.dist-info/METADATA
lv_athena_pkg-0.0.3.dist-info/WHEEL
lv_athena_pkg-0.0.3.dist-info/top_level.txt
lv_athena_pkg-0.0.3.dist-info/RECORD
