Metadata-Version: 2.1
Name: lv-athena-pkg
Version: 0.0.3
Summary: A package to extract information from s3 via athena
Home-page: https://bitbucket.org/leavyco/lv-athena-pck
Author: Sofiene Ben Romdhane
Author-email: sofien@leavy.co
License: UNKNOWN
Platform: UNKNOWN
Classifier: Programming Language :: Python :: 3
Classifier: License :: OSI Approved :: MIT License
Classifier: Operating System :: OS Independent
Requires-Python: >=3.6
